{
    "section1": {
        "files": [
            {
                "url": "client/public/assets/04 - Team-Developers/4G_devCarts.png",
                "type": "image",
                "key": "4G_devCarts"
            },
            {
                "url": "client/public/assets/04 - Team-Developers/4G_devJeyz.png",
                "type": "image",
                "key": "4G_devJeyz"
            },
            {
                "url": "client/public/assets/04 - Team-Developers/4G_devSquishy.png",
                "type": "image",
                "key": "4G_devSquishy"
            },
            {
                "url": "assets/04 - Team-Developers/4G_devZoks.png",
                "type": "image",
                "key": "4G_devZoks",
                "normalMap": "client/public/assets/04 - Team-Developers/4G_devZoks.png"
            },
            {
                "url": "client/public/assets/04 - Team-Developers/4G_titleDEV.png",
                "type": "image",
                "key": "4G_titleDEV"
            }
        ]
    },
    "meta": {
        "app": "Phaser Editor 2D - Asset Pack Editor",
        "contentType": "phasereditor2d.pack.core.AssetContentType",
        "url": "https://phasereditor2d.com",
        "version": 2,
        "showAllFilesInBlocks": false,
        "visible": true
    }
}